Metadata-Version: 2.1
Name: torch-stream
Version: 0.0.1
Summary: Building blocks for Continual Inference Networks in PyTorch
Home-page: https://github.com/lukashedegaard/continual-inference
Author: Lukas Hedegaard
Author-email: lukasxhedegaard@gmail.com
License: UNKNOWN
Keywords: deep learning,pytorch,AI,online,inference,continual
Platform: UNKNOWN
Classifier: Environment :: Console
Classifier: Natural Language :: English
Classifier: Development Status :: 4 - Beta
Classifier: Intended Audience :: Developers
Classifier: Topic :: Scientific/Engineering :: Artificial Intelligence
Classifier: Topic :: Scientific/Engineering :: Image Recognition
Classifier: Topic :: Scientific/Engineering :: Information Analysis
Classifier: License :: OSI Approved :: Apache Software License
Classifier: Operating System :: OS Independent
Classifier: Programming Language :: Python :: 3
Classifier: Programming Language :: Python :: 3.7
Classifier: Programming Language :: Python :: 3.8
Classifier: Programming Language :: Python :: 3.9
Requires-Dist: torch (>=1.9)
Provides-Extra: build
Requires-Dist: setuptools ; extra == 'build'
Requires-Dist: wheel ; extra == 'build'
Requires-Dist: twine ; extra == 'build'
Provides-Extra: dev
Requires-Dist: black ; extra == 'dev'
Requires-Dist: flake8 ; extra == 'dev'
Requires-Dist: flake8-black ; extra == 'dev'
Requires-Dist: isort (>=5.7) ; extra == 'dev'
Requires-Dist: pytest ; extra == 'dev'
Requires-Dist: pytest-cov ; extra == 'dev'
Requires-Dist: ptflops (>=0.6.8) ; extra == 'dev'
Requires-Dist: numpy ; extra == 'dev'
Requires-Dist: pytorch-lightning ; extra == 'dev'
Requires-Dist: onnxruntime (~=1.13) ; extra == 'dev'
Provides-Extra: docs
Requires-Dist: sphinx (==5.0.0) ; extra == 'docs'
Requires-Dist: sphinxcontrib.katex (==0.8.6) ; extra == 'docs'
Requires-Dist: matplotlib (==3.5.3) ; extra == 'docs'
Requires-Dist: tensorboard (==2.10.0) ; extra == 'docs'
Requires-Dist: python-etcd (==0.4.5) ; extra == 'docs'
Requires-Dist: sphinx-copybutton (==0.5.0) ; extra == 'docs'
Requires-Dist: sphinx-panels (==0.4.1) ; extra == 'docs'
Requires-Dist: myst-parser (==0.18.1) ; extra == 'docs'
